{
    "permisosComunes": [
        {
            "ID_TIPO_PERMISO": 10457,
            "DESCRIPCION_TIPO_PERMISO": "#BancoHorasParcial#",
            "ESTADO_TIPO_PERMISO": "enabled",
            "CON_GOCE_SUELDO": false,
            "MUESTRA_MARCA": false,
            "IDENTIFICADOR_EXTERNO_TIPO_PERMISO": -17,
            "PERMISO_PARCIAL": true,
            "PERMITE_MARCA": true,
            "PERMISO_POR_HORAS": true
        },
        {
            "ID_TIPO_PERMISO": 10454,
            "DESCRIPCION_TIPO_PERMISO": "#BancoHorasCompleto#",
            "ESTADO_TIPO_PERMISO": "enabled",
            "CON_GOCE_SUELDO": false,
            "MUESTRA_MARCA": false,
            "IDENTIFICADOR_EXTERNO_TIPO_PERMISO": -16,
            "PERMISO_PARCIAL": false
        },
        {
            "ID_TIPO_PERMISO": 6771,
            "DESCRIPCION_TIPO_PERMISO": "#BancoHoras#",
            "ESTADO_TIPO_PERMISO": "enabled",
            "CON_GOCE_SUELDO": false,
            "MUESTRA_MARCA": false,
            "IDENTIFICADOR_EXTERNO_TIPO_PERMISO": -15,
            "PERMISO_PARCIAL": false
        },
        {
            "ID_TIPO_PERMISO": 1177,
            "DESCRIPCION_TIPO_PERMISO": "Ley 20823",
            "ESTADO_TIPO_PERMISO": "enabled",
            "CON_GOCE_SUELDO": true,
            "IDENTIFICADOR_EXTERNO_TIPO_PERMISO": -14,
            "PERMISO_PARCIAL": false
        },
        {
            "ID_TIPO_PERMISO": 83,
            "DESCRIPCION_TIPO_PERMISO": "Permiso sin Goce",
            "ESTADO_TIPO_PERMISO": "enabled",
            "CON_GOCE_SUELDO": false,
            "IDENTIFICADOR_EXTERNO_TIPO_PERMISO": -13,
            "PERMISO_PARCIAL": false,
            "PERMITE_MARCA": true
        },
        {
            "ID_TIPO_PERMISO": 82,
            "DESCRIPCION_TIPO_PERMISO": "Permiso con Goce",
            "ESTADO_TIPO_PERMISO": "enabled",
            "CON_GOCE_SUELDO": true,
            "IDENTIFICADOR_EXTERNO_TIPO_PERMISO": -12,
            "PERMISO_PARCIAL": false,
            "PERMITE_MARCA": true
        },
        {
            "ID_TIPO_PERMISO": 81,
            "DESCRIPCION_TIPO_PERMISO": "Amamantamiento (Fuero)",
            "ESTADO_TIPO_PERMISO": "enabled",
            "CON_GOCE_SUELDO": true,
            "IDENTIFICADOR_EXTERNO_TIPO_PERMISO": -11,
            "PERMISO_PARCIAL": false,
            "PERMITE_MARCA": true
        },
        {
            "ID_TIPO_PERMISO": 80,
            "DESCRIPCION_TIPO_PERMISO": "Compensacion",
            "ESTADO_TIPO_PERMISO": "enabled",
            "CON_GOCE_SUELDO": true,
            "IDENTIFICADOR_EXTERNO_TIPO_PERMISO": -10,
            "PERMISO_PARCIAL": false,
            "PERMITE_MARCA": true
        },
        {
            "ID_TIPO_PERMISO": 79,
            "DESCRIPCION_TIPO_PERMISO": "Accidentes",
            "ESTADO_TIPO_PERMISO": "enabled",
            "CON_GOCE_SUELDO": true,
            "IDENTIFICADOR_EXTERNO_TIPO_PERMISO": -9,
            "PERMISO_PARCIAL": false,
            "PERMITE_MARCA": true
        },
        {
            "ID_TIPO_PERMISO": 78,
            "DESCRIPCION_TIPO_PERMISO": "Reunion",
            "ESTADO_TIPO_PERMISO": "enabled",
            "CON_GOCE_SUELDO": true,
            "IDENTIFICADOR_EXTERNO_TIPO_PERMISO": -8,
            "PERMISO_PARCIAL": false,
            "PERMITE_MARCA": true
        },
        {
            "ID_TIPO_PERMISO": 77,
            "DESCRIPCION_TIPO_PERMISO": "P. Sindical",
            "ESTADO_TIPO_PERMISO": "enabled",
            "CON_GOCE_SUELDO": true,
            "IDENTIFICADOR_EXTERNO_TIPO_PERMISO": -7,
            "PERMISO_PARCIAL": false,
            "PERMITE_MARCA": true
        },
        {
            "ID_TIPO_PERMISO": 76,
            "DESCRIPCION_TIPO_PERMISO": "Capacitacion",
            "ESTADO_TIPO_PERMISO": "enabled",
            "CON_GOCE_SUELDO": true,
            "IDENTIFICADOR_EXTERNO_TIPO_PERMISO": -6,
            "PERMISO_PARCIAL": false,
            "PERMITE_MARCA": true
        },
        {
            "ID_TIPO_PERMISO": 75,
            "DESCRIPCION_TIPO_PERMISO": "P. Fallecimiento",
            "ESTADO_TIPO_PERMISO": "enabled",
            "CON_GOCE_SUELDO": true,
            "IDENTIFICADOR_EXTERNO_TIPO_PERMISO": -5,
            "PERMISO_PARCIAL": false,
            "PERMITE_MARCA": true
        },
        {
            "ID_TIPO_PERMISO": 74,
            "DESCRIPCION_TIPO_PERMISO": "P. Administrativo",
            "ESTADO_TIPO_PERMISO": "enabled",
            "CON_GOCE_SUELDO": true,
            "IDENTIFICADOR_EXTERNO_TIPO_PERMISO": -4,
            "PERMISO_PARCIAL": false,
            "PERMITE_MARCA": true
        },
        {
            "ID_TIPO_PERMISO": 73,
            "DESCRIPCION_TIPO_PERMISO": "Otro",
            "ESTADO_TIPO_PERMISO": "enabled",
            "CON_GOCE_SUELDO": false,
            "IDENTIFICADOR_EXTERNO_TIPO_PERMISO": -3,
            "PERMISO_PARCIAL": false,
            "PERMITE_MARCA": true
        },
        {
            "ID_TIPO_PERMISO": 16,
            "DESCRIPCION_TIPO_PERMISO": "#licencia#",
            "ESTADO_TIPO_PERMISO": "enabled",
            "CON_GOCE_SUELDO": false,
            "IDENTIFICADOR_EXTERNO_TIPO_PERMISO": -2,
            "PERMISO_PARCIAL": false
        },
        {
            "ID_TIPO_PERMISO": 15,
            "DESCRIPCION_TIPO_PERMISO": "#vacaciones#",
            "ESTADO_TIPO_PERMISO": "enabled",
            "CON_GOCE_SUELDO": true,
            "IDENTIFICADOR_EXTERNO_TIPO_PERMISO": -1,
            "PERMISO_PARCIAL": false
        }
    ],
    "permisosEmpresa": [
        {
            "ID_TIPO_PERMISO": 3,
            "ID_EMPRESA": 1,
            "DESCRIPCION_TIPO_PERMISO": "Otro con Goce sueldo",
            "ESTADO_TIPO_PERMISO": "disabled",
            "CON_GOCE_SUELDO": true,
            "MUESTRA_MARCA": true,
            "IDENTIFICADOR_EXTERNO_TIPO_PERMISO": 1,
            "PERMISO_PARCIAL": false,
            "CANTIDAD_HORAS": "00:00"
        },
        {
            "ID_TIPO_PERMISO": 4,
            "ID_EMPRESA": 1,
            "DESCRIPCION_TIPO_PERMISO": "Otro sin Goce sueldo ",
            "ESTADO_TIPO_PERMISO": "disabled",
            "CON_GOCE_SUELDO": false,
            "MUESTRA_MARCA": true,
            "IDENTIFICADOR_EXTERNO_TIPO_PERMISO": 2,
            "PERMISO_PARCIAL": false,
            "CANTIDAD_HORAS": "00:00"
        },
        {
            "ID_TIPO_PERMISO": 5,
            "ID_EMPRESA": 1,
            "DESCRIPCION_TIPO_PERMISO": "P. Fallecimiento",
            "ESTADO_TIPO_PERMISO": "enabled",
            "CON_GOCE_SUELDO": true,
            "MUESTRA_MARCA": true,
            "IDENTIFICADOR_EXTERNO_TIPO_PERMISO": 3,
            "PERMISO_PARCIAL": false,
            "CANTIDAD_HORAS": "00:00"
        },
        {
            "ID_TIPO_PERMISO": 6,
            "ID_EMPRESA": 1,
            "DESCRIPCION_TIPO_PERMISO": "prueba permiso con goce  ",
            "ESTADO_TIPO_PERMISO": "disabled",
            "CON_GOCE_SUELDO": true,
            "MUESTRA_MARCA": true,
            "IDENTIFICADOR_EXTERNO_TIPO_PERMISO": 4,
            "PERMISO_PARCIAL": false,
            "CANTIDAD_HORAS": "00:00"
        },
        {
            "ID_TIPO_PERMISO": 7,
            "ID_EMPRESA": 1,
            "DESCRIPCION_TIPO_PERMISO": "prueba permiso sin goce ",
            "ESTADO_TIPO_PERMISO": "disabled",
            "CON_GOCE_SUELDO": false,
            "MUESTRA_MARCA": true,
            "IDENTIFICADOR_EXTERNO_TIPO_PERMISO": 5,
            "PERMISO_PARCIAL": false,
            "CANTIDAD_HORAS": "00:00"
        },
        {
            "ID_TIPO_PERMISO": 8,
            "ID_EMPRESA": 1,
            "DESCRIPCION_TIPO_PERMISO": "Reunión",
            "ESTADO_TIPO_PERMISO": "enabled",
            "CON_GOCE_SUELDO": true,
            "IDENTIFICADOR_EXTERNO_TIPO_PERMISO": 6,
            "PERMISO_PARCIAL": false,
            "PERMITE_MARCA": true
        },
        {
            "ID_TIPO_PERMISO": 9,
            "ID_EMPRESA": 1,
            "DESCRIPCION_TIPO_PERMISO": "Capacitación2",
            "ESTADO_TIPO_PERMISO": "enabled",
            "CON_GOCE_SUELDO": true,
            "MUESTRA_MARCA": true,
            "IDENTIFICADOR_EXTERNO_TIPO_PERMISO": 7,
            "PERMISO_PARCIAL": false,
            "CANTIDAD_HORAS": "00:00",
            "PERMITE_MARCA": true,
            "DESCUENTA_HORAS_TRABAJADAS": false,
            "CONTABILIZA_HORAS_TRABAJADAS": false
        },
        {
            "ID_TIPO_PERMISO": 10,
            "ID_EMPRESA": 1,
            "DESCRIPCION_TIPO_PERMISO": "JUSTIFICACION",
            "ESTADO_TIPO_PERMISO": "disabled",
            "CON_GOCE_SUELDO": false,
            "IDENTIFICADOR_EXTERNO_TIPO_PERMISO": 8,
            "PERMISO_PARCIAL": false,
            "PERMITE_MARCA": true
        },
        {
            "ID_TIPO_PERMISO": 11,
            "ID_EMPRESA": 1,
            "DESCRIPCION_TIPO_PERMISO": "prueba permiso desactivado con goce",
            "ESTADO_TIPO_PERMISO": "disabled",
            "CON_GOCE_SUELDO": false,
            "IDENTIFICADOR_EXTERNO_TIPO_PERMISO": 9,
            "PERMISO_PARCIAL": false,
            "PERMITE_MARCA": true
        },
        {
            "ID_TIPO_PERMISO": 12,
            "ID_EMPRESA": 1,
            "DESCRIPCION_TIPO_PERMISO": "prueba permiso desactivado sin goce",
            "ESTADO_TIPO_PERMISO": "disabled",
            "CON_GOCE_SUELDO": false,
            "IDENTIFICADOR_EXTERNO_TIPO_PERMISO": 10,
            "PERMISO_PARCIAL": false,
            "PERMITE_MARCA": true
        },
        {
            "ID_TIPO_PERMISO": 13,
            "ID_EMPRESA": 1,
            "DESCRIPCION_TIPO_PERMISO": "permiso desactivado con goce",
            "ESTADO_TIPO_PERMISO": "disabled",
            "CON_GOCE_SUELDO": false,
            "IDENTIFICADOR_EXTERNO_TIPO_PERMISO": 11,
            "PERMISO_PARCIAL": false,
            "PERMITE_MARCA": true
        },
        {
            "ID_TIPO_PERMISO": 14,
            "ID_EMPRESA": 1,
            "DESCRIPCION_TIPO_PERMISO": "permiso desactivado sin goce",
            "ESTADO_TIPO_PERMISO": "disabled",
            "CON_GOCE_SUELDO": false,
            "IDENTIFICADOR_EXTERNO_TIPO_PERMISO": 12,
            "PERMISO_PARCIAL": false,
            "PERMITE_MARCA": true
        },
        {
            "ID_TIPO_PERMISO": 19,
            "ID_EMPRESA": 1,
            "DESCRIPCION_TIPO_PERMISO": "prueba permiso",
            "ESTADO_TIPO_PERMISO": "disabled",
            "CON_GOCE_SUELDO": false,
            "IDENTIFICADOR_EXTERNO_TIPO_PERMISO": 13,
            "PERMISO_PARCIAL": false,
            "PERMITE_MARCA": true
        },
        {
            "ID_TIPO_PERMISO": 20,
            "ID_EMPRESA": 1,
            "DESCRIPCION_TIPO_PERMISO": "Pre- Natal ",
            "ESTADO_TIPO_PERMISO": "enabled",
            "CON_GOCE_SUELDO": true,
            "IDENTIFICADOR_EXTERNO_TIPO_PERMISO": 14,
            "PERMISO_PARCIAL": false,
            "PERMITE_MARCA": true
        },
        {
            "ID_TIPO_PERMISO": 26,
            "ID_EMPRESA": 1,
            "DESCRIPCION_TIPO_PERMISO": "Justificación",
            "ESTADO_TIPO_PERMISO": "enabled",
            "CON_GOCE_SUELDO": true,
            "IDENTIFICADOR_EXTERNO_TIPO_PERMISO": 15,
            "PERMISO_PARCIAL": false,
            "PERMITE_MARCA": true
        },
        {
            "ID_TIPO_PERMISO": 88,
            "ID_EMPRESA": 1,
            "DESCRIPCION_TIPO_PERMISO": "Sin Justificacion",
            "ESTADO_TIPO_PERMISO": "enabled",
            "CON_GOCE_SUELDO": false,
            "IDENTIFICADOR_EXTERNO_TIPO_PERMISO": 16,
            "PERMISO_PARCIAL": false,
            "PERMITE_MARCA": true
        },
        {
            "ID_TIPO_PERMISO": 89,
            "ID_EMPRESA": 1,
            "DESCRIPCION_TIPO_PERMISO": "Accidente",
            "ESTADO_TIPO_PERMISO": "enabled",
            "CON_GOCE_SUELDO": true,
            "IDENTIFICADOR_EXTERNO_TIPO_PERMISO": 17,
            "PERMISO_PARCIAL": false,
            "PERMITE_MARCA": true
        },
        {
            "ID_TIPO_PERMISO": 463,
            "ID_EMPRESA": 1,
            "DESCRIPCION_TIPO_PERMISO": "Permiso Matrimonio",
            "ESTADO_TIPO_PERMISO": "enabled",
            "CON_GOCE_SUELDO": true,
            "IDENTIFICADOR_EXTERNO_TIPO_PERMISO": 18,
            "PERMISO_PARCIAL": false,
            "PERMITE_MARCA": true
        },
        {
            "ID_TIPO_PERMISO": 490,
            "ID_EMPRESA": 1,
            "DESCRIPCION_TIPO_PERMISO": "dia de cumpleaños",
            "ESTADO_TIPO_PERMISO": "enabled",
            "CON_GOCE_SUELDO": true,
            "IDENTIFICADOR_EXTERNO_TIPO_PERMISO": 19,
            "PERMISO_PARCIAL": false,
            "PERMITE_MARCA": true
        },
        {
            "ID_TIPO_PERMISO": 656,
            "ID_EMPRESA": 1,
            "DESCRIPCION_TIPO_PERMISO": "prueba001",
            "ESTADO_TIPO_PERMISO": "enabled",
            "CON_GOCE_SUELDO": true,
            "MUESTRA_MARCA": true,
            "IDENTIFICADOR_EXTERNO_TIPO_PERMISO": 20,
            "PERMISO_PARCIAL": false,
            "CANTIDAD_HORAS": "00:00"
        },
        {
            "ID_TIPO_PERMISO": 710,
            "ID_EMPRESA": 1,
            "DESCRIPCION_TIPO_PERMISO": "Permiso Prueba QA",
            "ESTADO_TIPO_PERMISO": "enabled",
            "CON_GOCE_SUELDO": false,
            "IDENTIFICADOR_EXTERNO_TIPO_PERMISO": 21,
            "PERMISO_PARCIAL": false,
            "PERMITE_MARCA": true
        },
        {
            "ID_TIPO_PERMISO": 739,
            "ID_EMPRESA": 1,
            "DESCRIPCION_TIPO_PERMISO": "permiso de prueba 11 de junio del 2015",
            "ESTADO_TIPO_PERMISO": "enabled",
            "CON_GOCE_SUELDO": true,
            "IDENTIFICADOR_EXTERNO_TIPO_PERMISO": 22,
            "PERMISO_PARCIAL": false,
            "PERMITE_MARCA": true
        },
        {
            "ID_TIPO_PERMISO": 740,
            "ID_EMPRESA": 1,
            "DESCRIPCION_TIPO_PERMISO": "permiso con goce",
            "ESTADO_TIPO_PERMISO": "enabled",
            "CON_GOCE_SUELDO": true,
            "IDENTIFICADOR_EXTERNO_TIPO_PERMISO": 23,
            "PERMISO_PARCIAL": false,
            "PERMITE_MARCA": true
        },
        {
            "ID_TIPO_PERMISO": 741,
            "ID_EMPRESA": 1,
            "DESCRIPCION_TIPO_PERMISO": "permiso sin goce",
            "ESTADO_TIPO_PERMISO": "enabled",
            "CON_GOCE_SUELDO": false,
            "MUESTRA_MARCA": true,
            "IDENTIFICADOR_EXTERNO_TIPO_PERMISO": 24,
            "PERMISO_PARCIAL": false,
            "PERMITE_MARCA": true
        },
        {
            "ID_TIPO_PERMISO": 755,
            "ID_EMPRESA": 1,
            "DESCRIPCION_TIPO_PERMISO": "Licencia Medica",
            "ESTADO_TIPO_PERMISO": "enabled",
            "CON_GOCE_SUELDO": false,
            "IDENTIFICADOR_EXTERNO_TIPO_PERMISO": 25,
            "PERMISO_PARCIAL": false,
            "PERMITE_MARCA": true
        },
        {
            "ID_TIPO_PERMISO": 871,
            "ID_EMPRESA": 1,
            "DESCRIPCION_TIPO_PERMISO": "Prueba AutoInc",
            "ESTADO_TIPO_PERMISO": "enabled",
            "CON_GOCE_SUELDO": true,
            "IDENTIFICADOR_EXTERNO_TIPO_PERMISO": 26,
            "PERMISO_PARCIAL": false,
            "PERMITE_MARCA": true
        },
        {
            "ID_TIPO_PERMISO": 907,
            "ID_EMPRESA": 1,
            "DESCRIPCION_TIPO_PERMISO": "cumplea%C3%B1os",
            "ESTADO_TIPO_PERMISO": "enabled",
            "CON_GOCE_SUELDO": true,
            "IDENTIFICADOR_EXTERNO_TIPO_PERMISO": 27,
            "PERMISO_PARCIAL": false,
            "PERMITE_MARCA": true
        },
        {
            "ID_TIPO_PERMISO": 914,
            "ID_EMPRESA": 1,
            "DESCRIPCION_TIPO_PERMISO": "hora medico",
            "ESTADO_TIPO_PERMISO": "enabled",
            "CON_GOCE_SUELDO": true,
            "IDENTIFICADOR_EXTERNO_TIPO_PERMISO": 28,
            "PERMISO_PARCIAL": false,
            "PERMITE_MARCA": true
        },
        {
            "ID_TIPO_PERMISO": 924,
            "ID_EMPRESA": 1,
            "DESCRIPCION_TIPO_PERMISO": "PAIS EXTRANJERO (PERU)",
            "ESTADO_TIPO_PERMISO": "enabled",
            "CON_GOCE_SUELDO": true,
            "MUESTRA_MARCA": true,
            "IDENTIFICADOR_EXTERNO_TIPO_PERMISO": 29,
            "PERMISO_PARCIAL": false,
            "PERMITE_MARCA": true
        },
        {
            "ID_TIPO_PERMISO": 1019,
            "ID_EMPRESA": 1,
            "DESCRIPCION_TIPO_PERMISO": "PASEO EMPRESA",
            "ESTADO_TIPO_PERMISO": "enabled",
            "CON_GOCE_SUELDO": true,
            "IDENTIFICADOR_EXTERNO_TIPO_PERMISO": 30,
            "PERMISO_PARCIAL": false,
            "PERMITE_MARCA": true
        },
        {
            "ID_TIPO_PERMISO": 1167,
            "ID_EMPRESA": 1,
            "DESCRIPCION_TIPO_PERMISO": "test",
            "ESTADO_TIPO_PERMISO": "enabled",
            "CON_GOCE_SUELDO": true,
            "IDENTIFICADOR_EXTERNO_TIPO_PERMISO": 35,
            "PERMISO_PARCIAL": false,
            "CANTIDAD_HORAS": "00:00"
        },
        {
            "ID_TIPO_PERMISO": 1334,
            "ID_EMPRESA": 1,
            "DESCRIPCION_TIPO_PERMISO": "MEDIO DIA",
            "ESTADO_TIPO_PERMISO": "enabled",
            "CON_GOCE_SUELDO": true,
            "IDENTIFICADOR_EXTERNO_TIPO_PERMISO": 36,
            "PERMISO_PARCIAL": false,
            "CANTIDAD_HORAS": "00:00",
            "PERMITE_MARCA": true
        },
        {
            "ID_TIPO_PERMISO": 1335,
            "ID_EMPRESA": 1,
            "DESCRIPCION_TIPO_PERMISO": "DIA COMPLETO",
            "ESTADO_TIPO_PERMISO": "enabled",
            "CON_GOCE_SUELDO": true,
            "IDENTIFICADOR_EXTERNO_TIPO_PERMISO": 37,
            "PERMISO_PARCIAL": false,
            "CANTIDAD_HORAS": "00:00",
            "PERMITE_MARCA": true
        },
        {
            "ID_TIPO_PERMISO": 1353,
            "ID_EMPRESA": 1,
            "DESCRIPCION_TIPO_PERMISO": "TERRENO",
            "ESTADO_TIPO_PERMISO": "enabled",
            "CON_GOCE_SUELDO": true,
            "IDENTIFICADOR_EXTERNO_TIPO_PERMISO": 38,
            "PERMISO_PARCIAL": false,
            "CANTIDAD_HORAS": "00:00",
            "PERMITE_MARCA": true
        },
        {
            "ID_TIPO_PERMISO": 1440,
            "ID_EMPRESA": 1,
            "DESCRIPCION_TIPO_PERMISO": "FALTA",
            "ESTADO_TIPO_PERMISO": "enabled",
            "CON_GOCE_SUELDO": false,
            "IDENTIFICADOR_EXTERNO_TIPO_PERMISO": 40,
            "PERMISO_PARCIAL": false,
            "CANTIDAD_HORAS": "00:00",
            "PERMITE_MARCA": true
        },
        {
            "ID_TIPO_PERMISO": 1441,
            "ID_EMPRESA": 1,
            "DESCRIPCION_TIPO_PERMISO": "PERMISO",
            "ESTADO_TIPO_PERMISO": "enabled",
            "CON_GOCE_SUELDO": false,
            "IDENTIFICADOR_EXTERNO_TIPO_PERMISO": 41,
            "PERMISO_PARCIAL": false,
            "CANTIDAD_HORAS": "00:00",
            "PERMITE_MARCA": true
        },
        {
            "ID_TIPO_PERMISO": 1573,
            "ID_EMPRESA": 1,
            "DESCRIPCION_TIPO_PERMISO": "PERMISO POR NACIMIENTO",
            "ESTADO_TIPO_PERMISO": "enabled",
            "CON_GOCE_SUELDO": true,
            "IDENTIFICADOR_EXTERNO_TIPO_PERMISO": 42,
            "PERMISO_PARCIAL": false,
            "CANTIDAD_HORAS": "00:00",
            "PERMITE_MARCA": true
        },
        {
            "ID_TIPO_PERMISO": 1730,
            "ID_EMPRESA": 1,
            "DESCRIPCION_TIPO_PERMISO": "perm fijo x hora",
            "ESTADO_TIPO_PERMISO": "enabled",
            "CON_GOCE_SUELDO": true,
            "IDENTIFICADOR_EXTERNO_TIPO_PERMISO": 43,
            "PERMISO_PARCIAL": false,
            "CANTIDAD_HORAS": "00:00",
            "PERMITE_MARCA": true,
            "PERMISO_POR_HORAS": true
        },
        {
            "ID_TIPO_PERMISO": 1732,
            "ID_EMPRESA": 1,
            "DESCRIPCION_TIPO_PERMISO": "Justificacion Inasistencia",
            "ESTADO_TIPO_PERMISO": "enabled",
            "CON_GOCE_SUELDO": true,
            "IDENTIFICADOR_EXTERNO_TIPO_PERMISO": 44,
            "PERMISO_PARCIAL": false,
            "CANTIDAD_HORAS": "00:00",
            "PERMITE_MARCA": true,
            "PERMISO_POR_HORAS": true
        },
        {
            "ID_TIPO_PERMISO": 1873,
            "ID_EMPRESA": 1,
            "DESCRIPCION_TIPO_PERMISO": "TERRENO (CONCEPCIÓN)",
            "ESTADO_TIPO_PERMISO": "enabled",
            "CON_GOCE_SUELDO": true,
            "IDENTIFICADOR_EXTERNO_TIPO_PERMISO": 45,
            "PERMISO_PARCIAL": false,
            "CANTIDAD_HORAS": "00:00",
            "PERMISO_POR_HORAS": false
        },
        {
            "ID_TIPO_PERMISO": 2056,
            "ID_EMPRESA": 1,
            "DESCRIPCION_TIPO_PERMISO": "Prueba Victoria",
            "ESTADO_TIPO_PERMISO": "enabled",
            "CON_GOCE_SUELDO": true,
            "IDENTIFICADOR_EXTERNO_TIPO_PERMISO": 46,
            "PERMISO_PARCIAL": false,
            "CANTIDAD_HORAS": "00:00",
            "PERMITE_MARCA": true,
            "PERMISO_POR_HORAS": true
        },
        {
            "ID_TIPO_PERMISO": 2064,
            "ID_EMPRESA": 1,
            "DESCRIPCION_TIPO_PERMISO": "Salida Temprano",
            "ESTADO_TIPO_PERMISO": "enabled",
            "CON_GOCE_SUELDO": true,
            "IDENTIFICADOR_EXTERNO_TIPO_PERMISO": 47,
            "PERMISO_PARCIAL": false,
            "CANTIDAD_HORAS": "00:00",
            "PERMITE_MARCA": true,
            "PERMISO_POR_HORAS": true
        },
        {
            "ID_TIPO_PERMISO": 2150,
            "ID_EMPRESA": 1,
            "DESCRIPCION_TIPO_PERMISO": "Nuevo permiso fijo",
            "ESTADO_TIPO_PERMISO": "enabled",
            "CON_GOCE_SUELDO": true,
            "IDENTIFICADOR_EXTERNO_TIPO_PERMISO": 49,
            "PERMISO_PARCIAL": false,
            "CANTIDAD_HORAS": "00:00",
            "PERMITE_MARCA": true,
            "PERMISO_POR_HORAS": true
        },
        {
            "ID_TIPO_PERMISO": 2248,
            "ID_EMPRESA": 1,
            "DESCRIPCION_TIPO_PERMISO": "partido chile",
            "ESTADO_TIPO_PERMISO": "enabled",
            "CON_GOCE_SUELDO": true,
            "IDENTIFICADOR_EXTERNO_TIPO_PERMISO": 50,
            "PERMISO_PARCIAL": false,
            "CANTIDAD_HORAS": "00:00",
            "PERMITE_MARCA": true,
            "PERMISO_POR_HORAS": true
        },
        {
            "ID_TIPO_PERMISO": 2346,
            "ID_EMPRESA": 1,
            "DESCRIPCION_TIPO_PERMISO": "fijo prueba",
            "ESTADO_TIPO_PERMISO": "enabled",
            "CON_GOCE_SUELDO": true,
            "IDENTIFICADOR_EXTERNO_TIPO_PERMISO": 51,
            "PERMISO_PARCIAL": false,
            "CANTIDAD_HORAS": "00:00",
            "PERMITE_MARCA": true,
            "PERMISO_POR_HORAS": true
        },
        {
            "ID_TIPO_PERMISO": 2460,
            "ID_EMPRESA": 1,
            "DESCRIPCION_TIPO_PERMISO": "FERIADO",
            "ESTADO_TIPO_PERMISO": "enabled",
            "CON_GOCE_SUELDO": true,
            "IDENTIFICADOR_EXTERNO_TIPO_PERMISO": 52,
            "PERMISO_PARCIAL": false,
            "CANTIDAD_HORAS": "00:00",
            "PERMITE_MARCA": true,
            "PERMISO_POR_HORAS": false
        },
        {
            "ID_TIPO_PERMISO": 2534,
            "ID_EMPRESA": 1,
            "DESCRIPCION_TIPO_PERMISO": "Sin goce",
            "ESTADO_TIPO_PERMISO": "enabled",
            "CON_GOCE_SUELDO": false,
            "MUESTRA_MARCA": true,
            "IDENTIFICADOR_EXTERNO_TIPO_PERMISO": 53,
            "PERMISO_PARCIAL": false,
            "CANTIDAD_HORAS": "00:00",
            "PERMISO_POR_HORAS": true
        },
        {
            "ID_TIPO_PERMISO": 2539,
            "ID_EMPRESA": 1,
            "DESCRIPCION_TIPO_PERMISO": "Reposo Laboral",
            "ESTADO_TIPO_PERMISO": "enabled",
            "CON_GOCE_SUELDO": false,
            "IDENTIFICADOR_EXTERNO_TIPO_PERMISO": 54,
            "PERMISO_PARCIAL": false,
            "CANTIDAD_HORAS": "00:00",
            "PERMISO_POR_HORAS": false
        },
        {
            "ID_TIPO_PERMISO": 2587,
            "ID_EMPRESA": 1,
            "DESCRIPCION_TIPO_PERMISO": "partido",
            "ESTADO_TIPO_PERMISO": "enabled",
            "CON_GOCE_SUELDO": true,
            "IDENTIFICADOR_EXTERNO_TIPO_PERMISO": 55,
            "PERMISO_PARCIAL": false,
            "CANTIDAD_HORAS": "00:00",
            "PERMITE_MARCA": true,
            "PERMISO_POR_HORAS": true
        },
        {
            "ID_TIPO_PERMISO": 2653,
            "ID_EMPRESA": 1,
            "DESCRIPCION_TIPO_PERMISO": "Licencia Medica",
            "ESTADO_TIPO_PERMISO": "enabled",
            "CON_GOCE_SUELDO": false,
            "IDENTIFICADOR_EXTERNO_TIPO_PERMISO": 56,
            "PERMISO_PARCIAL": false,
            "CANTIDAD_HORAS": "00:00",
            "PERMITE_MARCA": true,
            "PERMISO_POR_HORAS": false
        },
        {
            "ID_TIPO_PERMISO": 2906,
            "ID_EMPRESA": 1,
            "DESCRIPCION_TIPO_PERMISO": "Prueba",
            "ESTADO_TIPO_PERMISO": "enabled",
            "CON_GOCE_SUELDO": true,
            "IDENTIFICADOR_EXTERNO_TIPO_PERMISO": 58,
            "PERMISO_PARCIAL": false,
            "CANTIDAD_HORAS": "00:00",
            "PERMITE_MARCA": true,
            "PERMISO_POR_HORAS": true
        },
        {
            "ID_TIPO_PERMISO": 4049,
            "ID_EMPRESA": 1,
            "DESCRIPCION_TIPO_PERMISO": "Disfrute Mañana",
            "ESTADO_TIPO_PERMISO": "enabled",
            "CON_GOCE_SUELDO": true,
            "IDENTIFICADOR_EXTERNO_TIPO_PERMISO": 62,
            "PERMISO_PARCIAL": false,
            "CANTIDAD_HORAS": "00:00",
            "PERMITE_MARCA": true,
            "PERMISO_POR_HORAS": true,
            "DESCUENTA_HORAS_TRABAJADAS": false
        },
        {
            "ID_TIPO_PERMISO": 4739,
            "ID_EMPRESA": 1,
            "DESCRIPCION_TIPO_PERMISO": "licencia especial",
            "ESTADO_TIPO_PERMISO": "enabled",
            "CON_GOCE_SUELDO": true,
            "IDENTIFICADOR_EXTERNO_TIPO_PERMISO": 63,
            "PERMISO_PARCIAL": false,
            "CANTIDAD_HORAS": "00:00",
            "DESCUENTA_HORAS_TRABAJADAS": false,
            "CONTABILIZA_HORAS_TRABAJADAS": false
        },
        {
            "ID_TIPO_PERMISO": 4740,
            "ID_EMPRESA": 1,
            "DESCRIPCION_TIPO_PERMISO": "licencia especial 2",
            "ESTADO_TIPO_PERMISO": "enabled",
            "CON_GOCE_SUELDO": true,
            "IDENTIFICADOR_EXTERNO_TIPO_PERMISO": 64,
            "PERMISO_PARCIAL": false,
            "CANTIDAD_HORAS": "00:00",
            "DESCUENTA_HORAS_TRABAJADAS": false,
            "CONTABILIZA_HORAS_TRABAJADAS": false
        },
        {
            "ID_TIPO_PERMISO": 5930,
            "ID_EMPRESA": 1,
            "DESCRIPCION_TIPO_PERMISO": "FINIQUITADO",
            "ESTADO_TIPO_PERMISO": "enabled",
            "CON_GOCE_SUELDO": false,
            "IDENTIFICADOR_EXTERNO_TIPO_PERMISO": 69,
            "PERMISO_PARCIAL": false,
            "CANTIDAD_HORAS": "00:00",
            "DESCUENTA_HORAS_TRABAJADAS": false,
            "CONTABILIZA_HORAS_TRABAJADAS": false
        },
        {
            "ID_TIPO_PERMISO": 5957,
            "ID_EMPRESA": 1,
            "DESCRIPCION_TIPO_PERMISO": "abc",
            "ESTADO_TIPO_PERMISO": "enabled",
            "CON_GOCE_SUELDO": true,
            "MUESTRA_MARCA": true,
            "IDENTIFICADOR_EXTERNO_TIPO_PERMISO": 70,
            "PERMISO_PARCIAL": false,
            "CANTIDAD_HORAS": "01:15",
            "PERMITE_MARCA": true,
            "PERMISO_POR_HORAS": true,
            "DESCUENTA_HORAS_TRABAJADAS": false,
            "CONTABILIZA_HORAS_TRABAJADAS": false
        },
        {
            "ID_TIPO_PERMISO": 5981,
            "ID_EMPRESA": 1,
            "DESCRIPCION_TIPO_PERMISO": "Inasistencia Justificada",
            "ESTADO_TIPO_PERMISO": "enabled",
            "CON_GOCE_SUELDO": false,
            "IDENTIFICADOR_EXTERNO_TIPO_PERMISO": 72,
            "PERMISO_PARCIAL": false,
            "CANTIDAD_HORAS": "00:00",
            "DESCUENTA_HORAS_TRABAJADAS": false,
            "CONTABILIZA_HORAS_TRABAJADAS": false
        },
        {
            "ID_TIPO_PERMISO": 6553,
            "ID_EMPRESA": 1,
            "DESCRIPCION_TIPO_PERMISO": "testcito",
            "ESTADO_TIPO_PERMISO": "enabled",
            "CON_GOCE_SUELDO": true,
            "MUESTRA_MARCA": true,
            "IDENTIFICADOR_EXTERNO_TIPO_PERMISO": 73,
            "PERMISO_PARCIAL": false,
            "CANTIDAD_HORAS": "00:00",
            "PERMITE_MARCA": true,
            "PERMISO_POR_HORAS": true,
            "DESCUENTA_HORAS_TRABAJADAS": false,
            "CONTABILIZA_HORAS_TRABAJADAS": true
        },
        {
            "ID_TIPO_PERMISO": 6772,
            "ID_EMPRESA": 1,
            "DESCRIPCION_TIPO_PERMISO": "A001_testjuanfra",
            "ESTADO_TIPO_PERMISO": "enabled",
            "CON_GOCE_SUELDO": true,
            "IDENTIFICADOR_EXTERNO_TIPO_PERMISO": 74,
            "PERMISO_PARCIAL": false,
            "CANTIDAD_HORAS": "00:00",
            "PERMITE_MARCA": true,
            "DESCUENTA_HORAS_TRABAJADAS": false,
            "CONTABILIZA_HORAS_TRABAJADAS": false
        },
        {
            "ID_TIPO_PERMISO": 6835,
            "ID_EMPRESA": 1,
            "DESCRIPCION_TIPO_PERMISO": "Certificado Medico por el Día",
            "ESTADO_TIPO_PERMISO": "enabled",
            "CON_GOCE_SUELDO": true,
            "IDENTIFICADOR_EXTERNO_TIPO_PERMISO": 75,
            "PERMISO_PARCIAL": false,
            "CANTIDAD_HORAS": "00:00",
            "DESCUENTA_HORAS_TRABAJADAS": false,
            "CONTABILIZA_HORAS_TRABAJADAS": false
        },
        {
            "ID_TIPO_PERMISO": 7289,
            "ID_EMPRESA": 1,
            "DESCRIPCION_TIPO_PERMISO": "Art 22",
            "ESTADO_TIPO_PERMISO": "enabled",
            "CON_GOCE_SUELDO": true,
            "IDENTIFICADOR_EXTERNO_TIPO_PERMISO": 76,
            "PERMISO_PARCIAL": false,
            "CANTIDAD_HORAS": "00:00",
            "PERMITE_MARCA": true,
            "DESCUENTA_HORAS_TRABAJADAS": false,
            "CONTABILIZA_HORAS_TRABAJADAS": false
        },
        {
            "ID_TIPO_PERMISO": 7706,
            "ID_EMPRESA": 1,
            "DESCRIPCION_TIPO_PERMISO": "Ausente",
            "ESTADO_TIPO_PERMISO": "enabled",
            "CON_GOCE_SUELDO": false,
            "IDENTIFICADOR_EXTERNO_TIPO_PERMISO": 78,
            "PERMISO_PARCIAL": false,
            "CANTIDAD_HORAS": "00:00",
            "DESCUENTA_HORAS_TRABAJADAS": false,
            "CONTABILIZA_HORAS_TRABAJADAS": false
        },
        {
            "ID_TIPO_PERMISO": 8520,
            "ID_EMPRESA": 1,
            "DESCRIPCION_TIPO_PERMISO": "FPH Con Goce",
            "ESTADO_TIPO_PERMISO": "enabled",
            "CON_GOCE_SUELDO": true,
            "MUESTRA_MARCA": true,
            "IDENTIFICADOR_EXTERNO_TIPO_PERMISO": 79,
            "PERMISO_PARCIAL": false,
            "CANTIDAD_HORAS": "00:00",
            "PERMITE_MARCA": true,
            "PERMISO_POR_HORAS": true,
            "DESCUENTA_HORAS_TRABAJADAS": false,
            "CONTABILIZA_HORAS_TRABAJADAS": true
        },
        {
            "ID_TIPO_PERMISO": 10197,
            "ID_EMPRESA": 1,
            "DESCRIPCION_TIPO_PERMISO": "Teletrabajo",
            "ESTADO_TIPO_PERMISO": "enabled",
            "CON_GOCE_SUELDO": true,
            "IDENTIFICADOR_EXTERNO_TIPO_PERMISO": 83,
            "PERMISO_PARCIAL": false,
            "CANTIDAD_HORAS": "00:00",
            "DESCUENTA_HORAS_TRABAJADAS": false,
            "CONTABILIZA_HORAS_TRABAJADAS": false
        },
        {
            "ID_TIPO_PERMISO": 10198,
            "ID_EMPRESA": 1,
            "DESCRIPCION_TIPO_PERMISO": "Suspension de contrato",
            "ESTADO_TIPO_PERMISO": "enabled",
            "CON_GOCE_SUELDO": false,
            "IDENTIFICADOR_EXTERNO_TIPO_PERMISO": 84,
            "PERMISO_PARCIAL": false,
            "CANTIDAD_HORAS": "00:00",
            "DESCUENTA_HORAS_TRABAJADAS": false,
            "CONTABILIZA_HORAS_TRABAJADAS": false
        }
    ],
    "permisosParciales": [
        {
            "ID_TIPO_PERMISO": 2021,
            "ID_EMPRESA": 1,
            "DESCRIPCION_TIPO_PERMISO": "PERMISO 2 HORAS",
            "ESTADO_TIPO_PERMISO": "enabled",
            "CON_GOCE_SUELDO": true,
            "MUESTRA_MARCA": true,
            "PERMISO_PARCIAL": true,
            "CANTIDAD_HORAS": "02:00",
            "PERMITE_MARCA": true,
            "PERMISO_POR_HORAS": false,
            "DESCUENTA_HORAS_TRABAJADAS": false,
            "CONTABILIZA_HORAS_TRABAJADAS": true
        },
        {
            "ID_TIPO_PERMISO": 10492,
            "ID_EMPRESA": 1,
            "DESCRIPCION_TIPO_PERMISO": "permiso test cpedalino",
            "ESTADO_TIPO_PERMISO": "enabled",
            "CON_GOCE_SUELDO": true,
            "IDENTIFICADOR_EXTERNO_TIPO_PERMISO": 26,
            "PERMISO_PARCIAL": true,
            "CANTIDAD_HORAS": "2",
            "PERMITE_MARCA": true
        },
        {
            "ID_TIPO_PERMISO": 10493,
            "ID_EMPRESA": 1,
            "DESCRIPCION_TIPO_PERMISO": "permiso test cpedalino",
            "ESTADO_TIPO_PERMISO": "enabled",
            "CON_GOCE_SUELDO": true,
            "IDENTIFICADOR_EXTERNO_TIPO_PERMISO": 26,
            "PERMISO_PARCIAL": true,
            "CANTIDAD_HORAS": "2",
            "PERMITE_MARCA": true
        },
        {
            "ID_TIPO_PERMISO": 1020,
            "ID_EMPRESA": 1,
            "DESCRIPCION_TIPO_PERMISO": "Fuero Maternal",
            "ESTADO_TIPO_PERMISO": "enabled",
            "CON_GOCE_SUELDO": true,
            "IDENTIFICADOR_EXTERNO_TIPO_PERMISO": 31,
            "PERMISO_PARCIAL": true,
            "CANTIDAD_HORAS": "01:00",
            "PERMITE_MARCA": true
        },
        {
            "ID_TIPO_PERMISO": 1021,
            "ID_EMPRESA": 1,
            "DESCRIPCION_TIPO_PERMISO": "Fuero Maternal 2",
            "ESTADO_TIPO_PERMISO": "enabled",
            "CON_GOCE_SUELDO": true,
            "IDENTIFICADOR_EXTERNO_TIPO_PERMISO": 32,
            "PERMISO_PARCIAL": true,
            "CANTIDAD_HORAS": "01:00",
            "PERMITE_MARCA": true
        },
        {
            "ID_TIPO_PERMISO": 1056,
            "ID_EMPRESA": 1,
            "DESCRIPCION_TIPO_PERMISO": "CAPACITACION",
            "ESTADO_TIPO_PERMISO": "enabled",
            "CON_GOCE_SUELDO": true,
            "IDENTIFICADOR_EXTERNO_TIPO_PERMISO": 33,
            "PERMISO_PARCIAL": true,
            "CANTIDAD_HORAS": "02:00",
            "PERMITE_MARCA": true
        },
        {
            "ID_TIPO_PERMISO": 1077,
            "ID_EMPRESA": 1,
            "DESCRIPCION_TIPO_PERMISO": "Salida anticipada",
            "ESTADO_TIPO_PERMISO": "disabled",
            "CON_GOCE_SUELDO": true,
            "MUESTRA_MARCA": true,
            "IDENTIFICADOR_EXTERNO_TIPO_PERMISO": 34,
            "PERMISO_PARCIAL": true,
            "CANTIDAD_HORAS": "02:00",
            "PERMITE_MARCA": true
        },
        {
            "ID_TIPO_PERMISO": 1159,
            "ID_EMPRESA": 1,
            "DESCRIPCION_TIPO_PERMISO": "joven com 2 ohras",
            "ESTADO_TIPO_PERMISO": "enabled",
            "CON_GOCE_SUELDO": true,
            "MUESTRA_MARCA": true,
            "IDENTIFICADOR_EXTERNO_TIPO_PERMISO": 34,
            "PERMISO_PARCIAL": true,
            "CANTIDAD_HORAS": "03:00",
            "PERMITE_MARCA": true,
            "PERMISO_POR_HORAS": false,
            "DESCUENTA_HORAS_TRABAJADAS": false
        },
        {
            "ID_TIPO_PERMISO": 1354,
            "ID_EMPRESA": 1,
            "DESCRIPCION_TIPO_PERMISO": "PERMISO",
            "ESTADO_TIPO_PERMISO": "enabled",
            "CON_GOCE_SUELDO": true,
            "IDENTIFICADOR_EXTERNO_TIPO_PERMISO": 39,
            "PERMISO_PARCIAL": true,
            "CANTIDAD_HORAS": "00:30",
            "PERMITE_MARCA": true
        },
        {
            "ID_TIPO_PERMISO": 2149,
            "ID_EMPRESA": 1,
            "DESCRIPCION_TIPO_PERMISO": "Nuevo permiso",
            "ESTADO_TIPO_PERMISO": "enabled",
            "CON_GOCE_SUELDO": true,
            "IDENTIFICADOR_EXTERNO_TIPO_PERMISO": 48,
            "PERMISO_PARCIAL": true,
            "CANTIDAD_HORAS": "05:00",
            "PERMITE_MARCA": true,
            "PERMISO_POR_HORAS": false
        },
        {
            "ID_TIPO_PERMISO": 2658,
            "ID_EMPRESA": 1,
            "DESCRIPCION_TIPO_PERMISO": "fiesta",
            "ESTADO_TIPO_PERMISO": "enabled",
            "CON_GOCE_SUELDO": true,
            "IDENTIFICADOR_EXTERNO_TIPO_PERMISO": 57,
            "PERMISO_PARCIAL": true,
            "CANTIDAD_HORAS": "00:00",
            "PERMITE_MARCA": true,
            "PERMISO_POR_HORAS": true
        },
        {
            "ID_TIPO_PERMISO": 3025,
            "ID_EMPRESA": 1,
            "DESCRIPCION_TIPO_PERMISO": "Dentista",
            "ESTADO_TIPO_PERMISO": "enabled",
            "CON_GOCE_SUELDO": false,
            "MUESTRA_MARCA": true,
            "IDENTIFICADOR_EXTERNO_TIPO_PERMISO": 59,
            "PERMISO_PARCIAL": true,
            "CANTIDAD_HORAS": "03:00",
            "PERMITE_MARCA": true,
            "PERMISO_POR_HORAS": false,
            "DESCUENTA_HORAS_TRABAJADAS": false,
            "CONTABILIZA_HORAS_TRABAJADAS": false
        },
        {
            "ID_TIPO_PERMISO": 3950,
            "ID_EMPRESA": 1,
            "DESCRIPCION_TIPO_PERMISO": "Permiso sindical",
            "ESTADO_TIPO_PERMISO": "enabled",
            "CON_GOCE_SUELDO": true,
            "MUESTRA_MARCA": true,
            "IDENTIFICADOR_EXTERNO_TIPO_PERMISO": 60,
            "PERMISO_PARCIAL": true,
            "CANTIDAD_HORAS": "01:00",
            "PERMITE_MARCA": true,
            "PERMISO_POR_HORAS": false,
            "DESCUENTA_HORAS_TRABAJADAS": false,
            "CONTABILIZA_HORAS_TRABAJADAS": true
        },
        {
            "ID_TIPO_PERMISO": 3952,
            "ID_EMPRESA": 1,
            "DESCRIPCION_TIPO_PERMISO": "Permiso de prueba",
            "ESTADO_TIPO_PERMISO": "enabled",
            "CON_GOCE_SUELDO": true,
            "IDENTIFICADOR_EXTERNO_TIPO_PERMISO": 61,
            "PERMISO_PARCIAL": true,
            "CANTIDAD_HORAS": "03:00",
            "PERMITE_MARCA": true,
            "PERMISO_POR_HORAS": false,
            "DESCUENTA_HORAS_TRABAJADAS": false
        },
        {
            "ID_TIPO_PERMISO": 5203,
            "ID_EMPRESA": 1,
            "DESCRIPCION_TIPO_PERMISO": "Fuero lactancia ",
            "ESTADO_TIPO_PERMISO": "enabled",
            "CON_GOCE_SUELDO": true,
            "MUESTRA_MARCA": true,
            "IDENTIFICADOR_EXTERNO_TIPO_PERMISO": 65,
            "PERMISO_PARCIAL": true,
            "CANTIDAD_HORAS": "01:00",
            "PERMITE_MARCA": true,
            "PERMISO_POR_HORAS": false,
            "DESCUENTA_HORAS_TRABAJADAS": false,
            "CONTABILIZA_HORAS_TRABAJADAS": false
        },
        {
            "ID_TIPO_PERMISO": 5204,
            "ID_EMPRESA": 1,
            "DESCRIPCION_TIPO_PERMISO": "Dentista 1 hora",
            "ESTADO_TIPO_PERMISO": "enabled",
            "CON_GOCE_SUELDO": true,
            "MUESTRA_MARCA": true,
            "IDENTIFICADOR_EXTERNO_TIPO_PERMISO": 66,
            "PERMISO_PARCIAL": true,
            "CANTIDAD_HORAS": "01:00",
            "PERMITE_MARCA": true,
            "PERMISO_POR_HORAS": false,
            "DESCUENTA_HORAS_TRABAJADAS": false,
            "CONTABILIZA_HORAS_TRABAJADAS": false
        },
        {
            "ID_TIPO_PERMISO": 5208,
            "ID_EMPRESA": 1,
            "DESCRIPCION_TIPO_PERMISO": "CUMPLEAÑOS 8",
            "ESTADO_TIPO_PERMISO": "enabled",
            "CON_GOCE_SUELDO": true,
            "IDENTIFICADOR_EXTERNO_TIPO_PERMISO": 67,
            "PERMISO_PARCIAL": true,
            "CANTIDAD_HORAS": "00:00",
            "PERMITE_MARCA": true,
            "PERMISO_POR_HORAS": true,
            "DESCUENTA_HORAS_TRABAJADAS": false,
            "CONTABILIZA_HORAS_TRABAJADAS": false
        },
        {
            "ID_TIPO_PERMISO": 5276,
            "ID_EMPRESA": 1,
            "DESCRIPCION_TIPO_PERMISO": "Permiso Navidad",
            "ESTADO_TIPO_PERMISO": "enabled",
            "CON_GOCE_SUELDO": true,
            "IDENTIFICADOR_EXTERNO_TIPO_PERMISO": 68,
            "PERMISO_PARCIAL": true,
            "CANTIDAD_HORAS": "04:07",
            "PERMITE_MARCA": true,
            "PERMISO_POR_HORAS": false,
            "DESCUENTA_HORAS_TRABAJADAS": false,
            "CONTABILIZA_HORAS_TRABAJADAS": false
        },
        {
            "ID_TIPO_PERMISO": 5960,
            "ID_EMPRESA": 1,
            "DESCRIPCION_TIPO_PERMISO": "123",
            "ESTADO_TIPO_PERMISO": "enabled",
            "CON_GOCE_SUELDO": true,
            "IDENTIFICADOR_EXTERNO_TIPO_PERMISO": 71,
            "PERMISO_PARCIAL": true,
            "CANTIDAD_HORAS": "01:15",
            "PERMITE_MARCA": true,
            "PERMISO_POR_HORAS": false,
            "DESCUENTA_HORAS_TRABAJADAS": false,
            "CONTABILIZA_HORAS_TRABAJADAS": true
        },
        {
            "ID_TIPO_PERMISO": 6786,
            "ID_EMPRESA": 1,
            "DESCRIPCION_TIPO_PERMISO": "Cumpleaños",
            "ESTADO_TIPO_PERMISO": "enabled",
            "CON_GOCE_SUELDO": true,
            "MUESTRA_MARCA": true,
            "IDENTIFICADOR_EXTERNO_TIPO_PERMISO": 75,
            "PERMISO_PARCIAL": true,
            "CANTIDAD_HORAS": "04:00",
            "PERMITE_MARCA": true,
            "PERMISO_POR_HORAS": false,
            "DESCUENTA_HORAS_TRABAJADAS": false,
            "CONTABILIZA_HORAS_TRABAJADAS": true
        },
        {
            "ID_TIPO_PERMISO": 7576,
            "ID_EMPRESA": 1,
            "DESCRIPCION_TIPO_PERMISO": "PERMISO AMAMANTAMIENTO",
            "ESTADO_TIPO_PERMISO": "enabled",
            "CON_GOCE_SUELDO": true,
            "MUESTRA_MARCA": true,
            "IDENTIFICADOR_EXTERNO_TIPO_PERMISO": 77,
            "PERMISO_PARCIAL": true,
            "CANTIDAD_HORAS": "01:00",
            "PERMITE_MARCA": true,
            "PERMISO_POR_HORAS": false,
            "DESCUENTA_HORAS_TRABAJADAS": false,
            "CONTABILIZA_HORAS_TRABAJADAS": false
        },
        {
            "ID_TIPO_PERMISO": 8572,
            "ID_EMPRESA": 1,
            "DESCRIPCION_TIPO_PERMISO": "pruebalac",
            "ESTADO_TIPO_PERMISO": "enabled",
            "CON_GOCE_SUELDO": true,
            "IDENTIFICADOR_EXTERNO_TIPO_PERMISO": 80,
            "PERMISO_PARCIAL": true,
            "CANTIDAD_HORAS": "00:00",
            "PERMITE_MARCA": true,
            "PERMISO_POR_HORAS": true,
            "DESCUENTA_HORAS_TRABAJADAS": false,
            "CONTABILIZA_HORAS_TRABAJADAS": false
        },
        {
            "ID_TIPO_PERMISO": 8596,
            "ID_EMPRESA": 1,
            "DESCRIPCION_TIPO_PERMISO": "pturba 1",
            "ESTADO_TIPO_PERMISO": "enabled",
            "CON_GOCE_SUELDO": true,
            "IDENTIFICADOR_EXTERNO_TIPO_PERMISO": 81,
            "PERMISO_PARCIAL": true,
            "CANTIDAD_HORAS": "00:00",
            "PERMITE_MARCA": true,
            "PERMISO_POR_HORAS": true,
            "DESCUENTA_HORAS_TRABAJADAS": false,
            "CONTABILIZA_HORAS_TRABAJADAS": true
        },
        {
            "ID_TIPO_PERMISO": 9516,
            "ID_EMPRESA": 1,
            "DESCRIPCION_TIPO_PERMISO": "Prueba Neko",
            "ESTADO_TIPO_PERMISO": "enabled",
            "CON_GOCE_SUELDO": true,
            "IDENTIFICADOR_EXTERNO_TIPO_PERMISO": 82,
            "PERMISO_PARCIAL": true,
            "CANTIDAD_HORAS": "00:00",
            "PERMITE_MARCA": true,
            "PERMISO_POR_HORAS": true,
            "DESCUENTA_HORAS_TRABAJADAS": false,
            "CONTABILIZA_HORAS_TRABAJADAS": false
        },
        {
            "ID_TIPO_PERMISO": 10470,
            "ID_EMPRESA": 1,
            "DESCRIPCION_TIPO_PERMISO": "FH Angel",
            "ESTADO_TIPO_PERMISO": "enabled",
            "CON_GOCE_SUELDO": true,
            "IDENTIFICADOR_EXTERNO_TIPO_PERMISO": 85,
            "PERMISO_PARCIAL": true,
            "CANTIDAD_HORAS": "04:00",
            "PERMITE_MARCA": true,
            "PERMISO_POR_HORAS": true,
            "DESCUENTA_HORAS_TRABAJADAS": false,
            "CONTABILIZA_HORAS_TRABAJADAS": false
        },
        {
            "ID_TIPO_PERMISO": 10471,
            "ID_EMPRESA": 1,
            "DESCRIPCION_TIPO_PERMISO": "FPH Desc Hrs",
            "ESTADO_TIPO_PERMISO": "enabled",
            "CON_GOCE_SUELDO": false,
            "IDENTIFICADOR_EXTERNO_TIPO_PERMISO": 86,
            "PERMISO_PARCIAL": true,
            "CANTIDAD_HORAS": "00:00",
            "PERMITE_MARCA": true,
            "PERMISO_POR_HORAS": true,
            "DESCUENTA_HORAS_TRABAJADAS": true,
            "CONTABILIZA_HORAS_TRABAJADAS": false
        },
        {
            "ID_TIPO_PERMISO": 10475,
            "ID_EMPRESA": 1,
            "DESCRIPCION_TIPO_PERMISO": "FPH Sin Goce",
            "ESTADO_TIPO_PERMISO": "enabled",
            "CON_GOCE_SUELDO": false,
            "IDENTIFICADOR_EXTERNO_TIPO_PERMISO": 87,
            "PERMISO_PARCIAL": true,
            "CANTIDAD_HORAS": "00:00",
            "PERMITE_MARCA": true,
            "PERMISO_POR_HORAS": true,
            "DESCUENTA_HORAS_TRABAJADAS": false,
            "CONTABILIZA_HORAS_TRABAJADAS": false
        },
        {
            "ID_TIPO_PERMISO": 10494,
            "ID_EMPRESA": 1,
            "DESCRIPCION_TIPO_PERMISO": "Prueba reportes",
            "ESTADO_TIPO_PERMISO": "enabled",
            "CON_GOCE_SUELDO": true,
            "IDENTIFICADOR_EXTERNO_TIPO_PERMISO": 88,
            "PERMISO_PARCIAL": true,
            "CANTIDAD_HORAS": "02:15",
            "PERMITE_MARCA": true,
            "PERMISO_POR_HORAS": false,
            "DESCUENTA_HORAS_TRABAJADAS": false,
            "CONTABILIZA_HORAS_TRABAJADAS": false
        },
        {
            "ID_TIPO_PERMISO": 10495,
            "ID_EMPRESA": 1,
            "DESCRIPCION_TIPO_PERMISO": "Prueba reportes - fijo",
            "ESTADO_TIPO_PERMISO": "enabled",
            "CON_GOCE_SUELDO": true,
            "IDENTIFICADOR_EXTERNO_TIPO_PERMISO": 89,
            "PERMISO_PARCIAL": true,
            "CANTIDAD_HORAS": "00:00",
            "PERMITE_MARCA": true,
            "PERMISO_POR_HORAS": true,
            "DESCUENTA_HORAS_TRABAJADAS": false,
            "CONTABILIZA_HORAS_TRABAJADAS": false
        },
        {
            "ID_TIPO_PERMISO": 10502,
            "ID_EMPRESA": 1,
            "DESCRIPCION_TIPO_PERMISO": "test 13",
            "ESTADO_TIPO_PERMISO": "enabled",
            "CON_GOCE_SUELDO": true,
            "IDENTIFICADOR_EXTERNO_TIPO_PERMISO": 90,
            "PERMISO_PARCIAL": true,
            "CANTIDAD_HORAS": "11:00",
            "PERMITE_MARCA": true,
            "PERMISO_POR_HORAS": false,
            "DESCUENTA_HORAS_TRABAJADAS": false,
            "CONTABILIZA_HORAS_TRABAJADAS": false
        }
    ]
}